survivorlib
